AUTHORS.rst
CONTRIBUTING.rst
HISTORY.rst
LICENSE
MANIFEST.in
README.rst
setup.cfg
setup.py
docs/Makefile
docs/conf.py
docs/index.rst
docs/make.bat
docs/_build/html/_static/file.png
docs/_build/html/_static/minus.png
docs/_build/html/_static/plus.png
docs/usage/bases.md
docs/usage/instalation.rst
docs/usage/usage.rst
exchange_escuela_it/__init__.py
exchange_escuela_it/converter.py
exchange_escuela_it.egg-info/PKG-INFO
exchange_escuela_it.egg-info/SOURCES.txt
exchange_escuela_it.egg-info/dependency_links.txt
exchange_escuela_it.egg-info/not-zip-safe
exchange_escuela_it.egg-info/requires.txt
exchange_escuela_it.egg-info/top_level.txt
exchange_escuela_it/bases/__init__.py
exchange_escuela_it/bases/base_exchange_converter.py
exchange_escuela_it/bases/exchange_converters/__init__.py
exchange_escuela_it/bases/exchange_converters/eur_converter.py
exchange_escuela_it/bases/exchange_converters/usd_converter.py
tests/__init__.py
tests/test_base_exchange_converter.py
tests/test_converter.py
tests/test_converters.py
tests/test_unittes_converter.py
tests/utils.py