Metadata-Version: 1.1
Name: exchange-escuela-it
Version: 0.1.2
Summary: Exchange lib example
Home-page: https://github.com/carlosmart626/exchange_escuela_it
Author: Carlos Martinez
Author-email: carlosmart626@gmail.com
License: MIT license
Keywords: exchange_escuela_it
Platform: UNKNOWN
Classifier: Development Status :: 2 - Pre-Alpha
Classifier: Intended Audience :: Developers
Classifier: License :: OSI Approved :: MIT License
Classifier: Natural Language :: English
Classifier: Programming Language :: Python :: 2
Classifier: Programming Language :: Python :: 2.7
Classifier: Programming Language :: Python :: 3
Classifier: Programming Language :: Python :: 3.4
Classifier: Programming Language :: Python :: 3.5
Classifier: Programming Language :: Python :: 3.6
Classifier: Programming Language :: Python :: 3.7
